mcp_server_vikingdb/__init__.py
mcp_server_vikingdb/server.py
mcp_server_vikingdb/vikingdb.py
mcp_server_vikingdb-0.1.2.dist-info/METADATA
mcp_server_vikingdb-0.1.2.dist-info/WHEEL
mcp_server_vikingdb-0.1.2.dist-info/entry_points.txt
mcp_server_vikingdb-0.1.2.dist-info/RECORD
