Metadata-Version: 2.3
Name: mcp-server-vikingdb
Version: 0.1.2
Summary: a mcp server for vikingdb store and search
Author-email: KashiwaByte <471314513@qq.com>
Requires-Python: >=3.10
Requires-Dist: aiohttp>=3.11.10
Requires-Dist: mcp>=1.1.0
Requires-Dist: python-dotenv>=1.0.1
Requires-Dist: volcengine>=1.0.164
